テスト対策/multiplexer.v
module multiplexer(a, b, c, f, s);
    input a, b, c;
    input[1:0] f;
    output reg s;

    always @(*) begin
        if(f == 2'b00)
            s = a;
        else if(f == 2'b01)
            s = b;
        else
            s = c;
    end

endmodule

テスト対策/multiplexer_sim.v
`timescale 1ns/1ns

module multiplexer_sim;
    reg a, b, c;
    reg[1:0] f;
    wire s;

    multiplexer multiplex1(a, b, c, f, s);

    initial begin
        forever begin
            a = 0; b = 0; c = 0;
            #10 a = 1;
            #10 a = 0; b = 1;
            #10 b = 0; c = 1;
            #10 ;
        end
    end

    initial begin
        f = 2'b00;
        #40 f = 2'b01;
        #40 f = 2'b10;
        #40 f = 2'b00;
        #40 $finish;
    end

    initial begin
        $monitor("a = %d, b = %d, c = %d, f = %d, s = %d",a, b, c, f, s);
        $dumpfile("multiplexer_sim.vcd");
        $dumpvars;
    end

endmodule

テスト対策/multiplexer_sim.vcd
$date
	Mon Feb  2 22:38:51 2026
$end
$version
	Icarus Verilog
$end
$timescale
	1ns
$end
$scope module multiplexer_sim $end
$var wire 1 ! s $end
$var reg 1 " a $end
$var reg 1 # b $end
$var reg 1 $ c $end
$var reg 2 % f [1:0] $end
$scope module multiplex1 $end
$var wire 1 " a $end
$var wire 1 # b $end
$var wire 1 $ c $end
$var wire 2 & f [1:0] $end
$var reg 1 ! s $end
$upscope $end
$upscope $end
$enddefinitions $end
$comment Show the parameter values. $end
$dumpall
$end
#0
$dumpvars
b0 &
b0 %
0$
0#
0"
0!
$end
#10
1!
1"
#20
0!
1#
0"
#30
1$
0#
#40
0$
b1 %
b1 &
#50
1"
#60
1!
1#
0"
#70
0!
1$
0#
#80
0$
b10 %
b10 &
#90
1"
#100
1#
0"
#110
1!
1$
0#
#120
0!
0$
b0 %
b0 &
#130
1!
1"
#140
0!
1#
0"
#150
1$
0#
#160
0$
